Workbook

Sheet Pre-Test
A1: Pre-Test Question Set (15) — LLMOps for Advanced Practitioners
A2: Scenario-based multiple choice. Difficulty easy–medium. Mapped to the LLMOps Advanced Labs (Azure ML / Azure Databricks). Answer key and rationale in columns I–J (hide before distribution).
A4: # | B4: Lab | C4: Difficulty | D4: Scenario / question | E4: A | F4: B | G4: C | H4: D | I4: Correct | J4: Rationale
A5: 1 | B5: L01 | C5: Easy | D5: Your team plans to serve a 31B-parameter dense model in bf16 on a single A100 80GB. Before any KV cache, roughly how much memory do the weights alone need? | E5: ~31 GB | F5: ~62 GB | G5: ~124 GB | H5: ~15 GB | I5: B | J5: bf16 = 2 bytes per parameter → 31 × 2 = 62 GB, already over one 80GB card once KV cache and overhead are added.
A6: 2 | B6: L01 | C6: Medium | D6: A colleague says a 26B-total / 4B-active MoE model needs only about 8 GB of GPU memory because 'only 4B parameters are active'. What is wrong? | E6: All expert weights must be resident; active parameters reduce compute, not memory | F6: Nothing — active parameters determine memory | G6: MoE models cannot run on a single GPU | H6: KV cache is not needed for MoE | I6: A | J6: Routing picks experts per token, but every expert's weights must be loaded. ~26B × 2 bytes ≈ 52 GB in bf16.
A7: 3 | B7: L02 | C7: Easy | D7: The edge team wants to run a small model on in-store devices with CPU only, using llama.cpp. Which shipping format do they need? | E7: ONNX | F7: AWQ int4 for vLLM | G7: GGUF | H7: safetensors bf16 | I7: C | J7: GGUF is llama.cpp's format and is the usual choice for CPU/edge inference.
A8: 4 | B8: L02 | C8: Medium | D8: After int4 quantisation with group size 256, one linear layer shows a much larger error than the others. Inspection shows a single very large weight. What is the most likely cause and the simplest first fix? | E8: int4 is unusable for that layer; keep it in fp32 | F8: The layer needs a bigger learning rate | G8: Rounding bug; re-run the converter | H8: An outlier inflates its group's scale; use a smaller group size (e.g. 64 or 128) | I8: D | J8: One outlier sets the absmax scale for the whole group; smaller groups limit the damage (AWQ/GPTQ address this more cleverly).
A9: 5 | B9: L03 | C9: Easy | D9: For an ad-copy generation API, product managers care most about how quickly the first words appear on screen. Which metric should the serving benchmark report for that? | E9: Time to first token (TTFT) p50/p95 | F9: GPU utilisation | G9: Throughput (tokens/s) | H9: Cold-start time | I9: A | J9: TTFT is the user-perceived responsiveness metric; throughput matters for cost, not first-word latency.
A10: 6 | B10: L03 | C10: Medium | D10: You need to serve many different Hugging Face models that change weekly, and the deployment must be online within two minutes of a model swap. Which engine choice best fits? | E10: Run the model in a Spark UDF | F10: vLLM (or SGLang) serving directly from the checkpoint | G10: Export to ONNX and use onnxruntime | H10: TensorRT-LLM with compiled engines | I10: B | J10: TensorRT-LLM's engine build step can take tens of minutes; vLLM/SGLang load checkpoints directly with a much faster cold start.
A11: 7 | B11: L04 | C11: Easy | D11: The recommendation team reports retrieval quality with recall@10 = 0.82. What does this number mean? | E11: On average 82% of the relevant items appear in the top 10 results | F11: 82% of queries return at least one result | G11: 82% of retrieved items are relevant | H11: The index answers in 82 ms | I11: A | J11: recall@k = |top-k ∩ relevant| / |relevant| (capped at k), averaged over queries.
A12: 8 | B12: L05 | C12: Easy | D12: Why is standard attention on a long sequence usually limited by memory bandwidth rather than arithmetic? | E12: Softmax is expensive | F12: Matrix multiplication is slow on GPUs | G12: GPUs have too few cores | H12: It materialises an N×N score matrix that must be written to and read from HBM | I12: D | J12: The N² score/probability matrices are the traffic; FlashAttention avoids materialising them.
A13: 9 | B13: L06 | C13: Medium | D13: An MoE serving dashboard shows expert 0 receiving 40% of tokens while the other seven get ~8% each. What operational effect should you expect? | E13: Higher accuracy | F13: The GPU holding expert 0 becomes the bottleneck while others idle; latency rises | G13: No effect — routing is free | H13: Lower memory use | I13: B | J13: Load imbalance leaves capacity unused on other experts/GPUs; capacity factors and load-balancing losses exist to fight this.
A14: 10 | B14: L07 | C14: Easy | D14: You fine-tune a 4B model with LoRA (rank 16) on attention projections. Roughly what fraction of parameters is trainable? | E14: Exactly 16% | F14: About half | G14: All of them | H14: Well under 1% | I14: D | J14: LoRA trains only small A and B matrices; trainable parameters are typically a fraction of a percent of the base model.
A15: 11 | B15: L08 | C15: Easy | D15: Nightly you must classify 5 million catalog titles into 8 taxonomy categories on a fixed budget. Which is the most cost-effective default? | E15: Zero-shot prompting of a 31B LLM per item | F15: Manual labelling | G15: A fine-tuned RoBERTa-class encoder classifier exported to ONNX and run in batch | H15: Embedding search against 8 category names with a 31B model | I15: C | J15: Encoder classifiers run thousands of items/second per node; LLM zero-shot costs tokens per item and is orders of magnitude more expensive for high-volume simple classification.
A16: 12 | B16: L09 | C16: Medium | D16: A new model version scores exact-match 0.86 (floor 0.80) but its output is missing the 'size' key in 15% of responses. Your CI gate only checks exact-match. What is the risk and the fix? | E16: Retrain with more epochs | F16: No risk — it passed the floor | G16: Lower the floor to 0.70 | H16: Downstream JSON parsers break; add a schema-validity check and a no-regression-vs-champion rule | I16: D | J16: A single metric hides structural regressions; gates should check schema validity and compare to the champion within a tolerance.
... A19: 15 | B19: L13 | C19: Easy | D19: Ten evaluation prompts also appear verbatim in the fine-tuning training set. What should the data pipeline do? | E19: Remove them from the evaluation set so eval stays independent | F19: Remove them from the training set | G19: Keep both — more data is better | H19: Duplicate them to balance | I19: A | J19: Eval must be clean and independent; train can keep its rows, the leaked items leave eval.

Sheet Post-Test
A1: Post-Test Question Set (15) — LLMOps for Advanced Practitioners
A2: Scenario-based multiple choice. Difficulty easy–medium. Mapped to the LLMOps Advanced Labs (Azure ML / Azure Databricks). Answer key and rationale in columns I–J (hide before distribution).
A4: # | B4: Lab | C4: Difficulty | D4: Scenario / question | E4: A | F4: B | G4: C | H4: D | I4: Correct | J4: Rationale
A5: 1 | B5: L01 | C5: Medium | D5: Using the lab's memory-fit formula, a dense 31B bf16 model with a KV cache of ~16 GB (batch 8, 8k context) and 10% overhead totals ~86 GB. With 90% usable memory per GPU, how many A100-80GB cards are needed? | E5: 2 | F5: 4 | G5: 1 | H5: 3 | I5: A | J5: 86 / (80 × 0.9 = 72) = 1.19 → ceil = 2. The KV cache and overhead push it over one card.
A6: 2 | B6: L02 | C6: Medium | D6: In L02 you exported a classifier to ONNX and checked prediction agreement with the source model on the full test set. Why is this check mandatory before shipping? | E6: ONNX files are always smaller | F6: It speeds up inference | G6: A converter can silently change behaviour; equivalence must be proven, not assumed | H6: onnxruntime requires it | I6: C | J6: Export equivalence is a release gate; a silent mismatch is a production incident.
A7: 3 | B7: L03 | C7: Medium | D7: Your harness measured TTFT p50 = 52 ms on a mock server configured for 50 ms first-token latency. The real vLLM run shows p95 TTFT rising sharply at concurrency 32. What is the most likely interpretation? | E7: Requests are queueing under continuous batching at that load; you are near the engine's capacity | F7: TTFT is not affected by load | G7: The harness is broken | H7: vLLM does not support concurrency | I7: A | J7: The mock validated the harness; the p95 growth is the real engine saturating — the point of testing three concurrency levels.
A8: 4 | B8: L03 | C8: Easy | D8: In the bake-off you must record TensorRT-LLM's engine-build time separately from its cold start. Why? | E8: Only vLLM has a cold start | F8: Engine build is billed differently | G8: Engine build is a one-off cost that changes the decision for short-lived vs long-lived deployments | H8: It is always zero | I8: C | J8: A long build is acceptable for a single long-lived model but not for weekly model swaps.
A9: 5 | B9: L04 | C9: Medium | D9: Brute-force search and your HNSW index agree on only 88% of top-10 results, below the 95% target. What is the right next action? | E9: Switch to keyword search | F9: Reduce k to 5 | G9: Accept it — approximate search is always lossy | H9: Tune index parameters (e.g. ef_search / M) and re-measure agreement against brute force | I9: D | J9: Exact search is the reference; index recall is tuned by its parameters and re-measured, not assumed.
A10: 6 | B10: L05 | C10: Medium | D10: In the tiled attention you wrote, why must the accumulated output be rescaled by exp(m_old − m_new) when a new block raises the running max? | E10: Because softmax is computed relative to the max; earlier partial sums were scaled with the old max and must be corrected | F10: To reduce memory | G10: It is optional and only improves speed | H10: To normalise the output to unit length | I10: A | J10: This is the online-softmax recurrence that makes streaming K/V blocks exact.
A11: 7 | B11: L05 | C11: Easy | D11: Your profiler trace shows attention kernels at 61% of decode time with eager attention and 34% with FlashAttention, with the same output. What changed? | E11: The model got smaller | F11: FLOPs were reduced | G11: HBM traffic for the N×N matrices was eliminated, so the kernel became less memory-bound | H11: Batch size increased | I11: C | J11: Same maths, less memory movement — the FlashAttention argument demonstrated by measurement.
A12: 8 | B12: L06 | C12: Medium | D12: At capacity factor 1.0 your skewed router drops 9% of tokens; at 1.25 it drops 1%. What is the trade-off of raising the capacity factor? | E12: Lower accuracy | F12: No trade-off — always use the highest | G12: More padding/compute and memory per expert for headroom versus fewer dropped tokens | H12: It disables routing | I12: C | J12: Capacity factor buys reliability with wasted capacity; balancing the router reduces the need for it.
A13: 9 | B13: L06 | C13: Easy | D13: Your MoE-vs-dense table shows Gemma 4 26B A4B at ~52 GB resident memory and ~13% of the dense 31B model's per-token compute. Which resource decides whether it fits on one A100-80GB? | E13: Network bandwidth | F13: Number of experts | G13: Compute | H13: Memory (weights + KV cache) | I13: D | J13: Feasibility is decided by resident memory; compute decides throughput and cost once it fits.
A14: 10 | B14: L07 | C14: Medium | D14: After LoRA training you 'merge and unload' before registering the model in Unity Catalog. What does the merge do and why is it safe? | E14: Converts to ONNX | F14: Deletes the adapter; behaviour changes | G14: Compresses the model to int4 | H14: Adds B·A (scaled) into W so the merged forward pass equals the adapter forward pass — proven in Step 2 of the lab | I14: D | J14: W_merged = W + (α/r)·B·A; the lab asserted adapter and merged outputs are equal.
A15: 11 | B15: L07 | C15: Easy | D15: Your fine-tuned Gemma model scores exact-match 0.78 on the eval set, while the rule-based baseline scores 0.95. Per the lab's acceptance policy, what happens? | E15: Ship the LLM — it is more modern | F15: Do not ship; a tuned model that loses to the rule baseline fails the gate | G15: Lower the floor to 0.75 | H15: Ship both | I15: B | J15: The floor and the baseline comparison exist precisely to stop this.
A16: 12 | B16: L08 | C16: Medium | D16: Your Spark pandas UDF for ONNX scoring runs slower than the single-node loop. The code creates a new InferenceSession inside the UDF function. What is the fix? | E16: Use more executors | F16: Cache the session at module level so it is created once per executor process, and raise the Arrow batch size | G16: Disable Arrow | H16: Switch to a Python UDF | I16: B | J16: Session creation per batch dominates; the lab caches the session and tunes maxRecordsPerBatch.
... A19: 15 | B19: L11 | C19: Medium | D19: In the autoscaling simulation a replica dies at minute 300 with a minimum of 2 replicas configured. Queue wait spikes briefly then recovers. Which two mechanisms produced the recovery? | E19: Larger batch size and FlashAttention | F19: Tensor parallelism and quantisation | G19: Spot pricing and caching | H19: Minimum-replica floor for HA plus scale-up when queue wait approaches the SLA | I19: D | J19: HA minimum keeps service alive; the scale-up rule restores capacity — the L11 simulation's two levers.

Sheet Pre-Test Answer Sheet
A1: Pre-Test answer sheet — participant enters A/B/C/D in column B; score computed by formula
A2: Participant name:
A4: # | B4: Your answer | C4: Correct | D4: Mark
A5: 1 | C5: ='Pre-Test'!I5 -> B | D5: =IF(B5="","",IF(B5=C5,1,0))
A6: 2 | C6: ='Pre-Test'!I6 -> A | D6: =IF(B6="","",IF(B6=C6,1,0))
A7: 3 | C7: ='Pre-Test'!I7 -> C | D7: =IF(B7="","",IF(B7=C7,1,0))
A8: 4 | C8: ='Pre-Test'!I8 -> D | D8: =IF(B8="","",IF(B8=C8,1,0))
A9: 5 | C9: ='Pre-Test'!I9 -> A | D9: =IF(B9="","",IF(B9=C9,1,0))
A10: 6 | C10: ='Pre-Test'!I10 -> B | D10: =IF(B10="","",IF(B10=C10,1,0))
A11: 7 | C11: ='Pre-Test'!I11 -> A | D11: =IF(B11="","",IF(B11=C11,1,0))
A12: 8 | C12: ='Pre-Test'!I12 -> D | D12: =IF(B12="","",IF(B12=C12,1,0))
A13: 9 | C13: ='Pre-Test'!I13 -> B | D13: =IF(B13="","",IF(B13=C13,1,0))
A14: 10 | C14: ='Pre-Test'!I14 -> D | D14: =IF(B14="","",IF(B14=C14,1,0))
A15: 11 | C15: ='Pre-Test'!I15 -> C | D15: =IF(B15="","",IF(B15=C15,1,0))
A16: 12 | C16: ='Pre-Test'!I16 -> D | D16: =IF(B16="","",IF(B16=C16,1,0))
... A19: 15 | C19: ='Pre-Test'!I19 -> A | D19: =IF(B19="","",IF(B19=C19,1,0))
A21: Score | B21: =SUM(D5:D19) -> 0 | C21: of 15 | D21: =IF(COUNT(D5:D19)=0,"",B21/15)

Sheet Post-Test Answer Sheet
A1: Post-Test answer sheet — participant enters A/B/C/D in column B; score computed by formula
A2: Participant name:
A4: # | B4: Your answer | C4: Correct | D4: Mark
A5: 1 | C5: ='Post-Test'!I5 -> A | D5: =IF(B5="","",IF(B5=C5,1,0))
A6: 2 | C6: ='Post-Test'!I6 -> C | D6: =IF(B6="","",IF(B6=C6,1,0))
A7: 3 | C7: ='Post-Test'!I7 -> A | D7: =IF(B7="","",IF(B7=C7,1,0))
A8: 4 | C8: ='Post-Test'!I8 -> C | D8: =IF(B8="","",IF(B8=C8,1,0))
A9: 5 | C9: ='Post-Test'!I9 -> D | D9: =IF(B9="","",IF(B9=C9,1,0))
A10: 6 | C10: ='Post-Test'!I10 -> A | D10: =IF(B10="","",IF(B10=C10,1,0))
A11: 7 | C11: ='Post-Test'!I11 -> C | D11: =IF(B11="","",IF(B11=C11,1,0))
A12: 8 | C12: ='Post-Test'!I12 -> C | D12: =IF(B12="","",IF(B12=C12,1,0))
A13: 9 | C13: ='Post-Test'!I13 -> D | D13: =IF(B13="","",IF(B13=C13,1,0))
A14: 10 | C14: ='Post-Test'!I14 -> D | D14: =IF(B14="","",IF(B14=C14,1,0))
A15: 11 | C15: ='Post-Test'!I15 -> B | D15: =IF(B15="","",IF(B15=C15,1,0))
A16: 12 | C16: ='Post-Test'!I16 -> B | D16: =IF(B16="","",IF(B16=C16,1,0))
... A19: 15 | C19: ='Post-Test'!I19 -> D | D19: =IF(B19="","",IF(B19=C19,1,0))
A21: Score | B21: =SUM(D5:D19) -> 0 | C21: of 15 | D21: =IF(COUNT(D5:D19)=0,"",B21/15)
